geopysc/__init__.py
geopysc/common.py
geopysc/geopysc.py
geopysc-0.0.4.dist-info/licenses/LICENSE
geopysc-0.0.4.dist-info/METADATA
geopysc-0.0.4.dist-info/WHEEL
geopysc-0.0.4.dist-info/entry_points.txt
geopysc-0.0.4.dist-info/top_level.txt
geopysc-0.0.4.dist-info/RECORD
